LICENSE.txt
README.md
setup.py
Modules/AdvancedCalculations.py
Modules/Calculator.py
Modules/Cluster.py
Modules/Dynamical.py
Modules/Ensemble.py
Modules/Minimizer.py
Modules/Optimizer.py
Modules/Parallel.py
Modules/Relax.py
Modules/SchaMinimizer.py
Modules/Tools.py
Modules/Utilities.py
Modules/__init__.py
Modules/aiida_ensemble.py
Modules/fourier_gradient.jl
SCHAModules/cell_force.f90
SCHAModules/get_cmat.f90
SCHAModules/get_emat.f90
SCHAModules/get_g.f90
SCHAModules/get_gradient_supercell.f90
SCHAModules/get_gradient_supercell_fast.f90
SCHAModules/get_odd_straight.f90
SCHAModules/get_odd_straight_with_v4.f90
SCHAModules/get_stress_tensor.f90
SCHAModules/get_upsilon_matrix.f90
SCHAModules/get_v3.f90
SCHAModules/get_v4.f90
SCHAModules/module_anharmonic.f90
SCHAModules/module_new_thermodynamic.f90
SCHAModules/module_stochastic.f90
SCHAModules/multiply_lambda_tensor.f90
python_sscha.egg-info/PKG-INFO
python_sscha.egg-info/SOURCES.txt
python_sscha.egg-info/dependency_links.txt
python_sscha.egg-info/top_level.txt
scripts/cluster_check.x
scripts/plot_frequencies.py
scripts/read_incomplete_ensemble.py
scripts/sscha
scripts/sscha-plot-data.py
scripts/static-vc-relax.pyx